briscas/__init__.py
briscas/game.py
briscas/main.py
briscas/util.py
briscas-1.0.dist-info/DESCRIPTION.rst
briscas-1.0.dist-info/METADATA
briscas-1.0.dist-info/RECORD
briscas-1.0.dist-info/WHEEL
briscas-1.0.dist-info/entry_points.txt
briscas-1.0.dist-info/metadata.json
briscas-1.0.dist-info/top_level.txt
