Metadata-Version: 2.0
Name: briscas
Version: 1.0
Summary: Library to model the briscas card game.
Home-page: https://github.com/bcollazo/briscas
Author: Bryan Collazo
Author-email: bcollazo2010@gmail.com
License: MIT
Download-URL: https://github.com/bcollazo/briscas/archive/1.0.tar.gz
Keywords: briscas,card,game,terminal,naipes
Platform: UNKNOWN
Classifier: Development Status :: 3 - Alpha
Classifier: License :: OSI Approved :: MIT License
Classifier: Topic :: Games/Entertainment
Classifier: Programming Language :: Python :: 2.7
Classifier: Programming Language :: Python :: 3.4
Classifier: Programming Language :: Python :: 3.5
Classifier: Programming Language :: Python :: 3.6
